fw_gdrive/__init__.py
fw_gdrive/gapi.py
fw_gdrive/utils.py
fw_gdrive-0.3.3.dist-info/LICENSE
fw_gdrive-0.3.3.dist-info/METADATA
fw_gdrive-0.3.3.dist-info/WHEEL
fw_gdrive-0.3.3.dist-info/RECORD
