Metadata-Version: 2.1
Name: fw-gdrive
Version: 0.3.3
Summary: Flyweheel Google Drive Integration Tools
Home-page: https://gitlab.com/flywheel-io/tools/lib/fw-gdrive
License: MIT
Keywords: Flywheel
Author: Flywheel
Author-email: support@flywheel.io
Requires-Python: >=3.7,<4.0
Classifier: License :: OSI Approved :: MIT License
Classifier: Programming Language :: Python :: 3
Classifier: Programming Language :: Python :: 3.7
Classifier: Programming Language :: Python :: 3.8
Classifier: Programming Language :: Python :: 3.9
Classifier: Programming Language :: Python :: 3.10
Classifier: Programming Language :: Python :: 3.11
Classifier: Topic :: Software Development :: Libraries :: Python Modules
Requires-Dist: google-api-python-client (>=2.32.0,<3.0.0)
Requires-Dist: oauth2client (>=4.1.3,<5.0.0)
Project-URL: Documentation, https://gitlab.com/flywheel-io/tools/lib/fw-gdrive
Project-URL: Repository, https://gitlab.com/flywheel-io/tools/lib/fw-gdrive
